rk4_sparse/__init__.py
rk4_sparse/__init__.py.in
rk4_sparse/_rk4_sparse_cpp.cpython-39-aarch64-linux-gnu.so
rk4_sparse/api.py
rk4_sparse/fast.py
rk4_sparse/rk4_py.py
rk4_sparse/utils.py
rk4_sparse_cpp.libs/libgomp-947d5fa1.so.1.0.0
rk4_sparse_cpp-0.2.10.dist-info/METADATA
rk4_sparse_cpp-0.2.10.dist-info/WHEEL
rk4_sparse_cpp-0.2.10.dist-info/RECORD
rk4_sparse_cpp-0.2.10.dist-info/licenses/LICENSE
