Metadata-Version: 2.2
Name: rk4-sparse-cpp
Version: 0.2.10
Summary: High-performance sparse matrix RK4 solver for quantum excitation dynamics
Keywords: quantum,dynamics,rk4,sparse,physics,simulation
Author-Email: Hiroki Tsusaka <tsusaka4research@gmail.com>
License: MIT License
Classifier: Development Status :: 4 - Beta
Classifier: Intended Audience :: Science/Research
Classifier: License :: OSI Approved :: MIT License
Classifier: Programming Language :: Python :: 3
Classifier: Programming Language :: Python :: 3.9
Classifier: Programming Language :: Python :: 3.10
Classifier: Programming Language :: Python :: 3.11
Classifier: Programming Language :: Python :: 3.12
Classifier: Programming Language :: C++
Classifier: Topic :: Scientific/Engineering :: Physics
Classifier: Topic :: Scientific/Engineering :: Mathematics
Project-URL: Homepage, https://github.com/1160-hrk/rk4-sparse-cpp
Project-URL: Documentation, https://github.com/1160-hrk/rk4-sparse-cpp/tree/main/docs
Project-URL: Repository, https://github.com/1160-hrk/rk4-sparse-cpp
Project-URL: Issues, https://github.com/1160-hrk/rk4-sparse-cpp/issues
Requires-Python: >=3.9
Requires-Dist: pybind11>=2.6.0
Requires-Dist: numpy>=1.20.0
Requires-Dist: scipy>=1.7.0
Requires-Dist: matplotlib>=3.3.0
Provides-Extra: dev
Requires-Dist: pytest>=6.0; extra == "dev"
Requires-Dist: pytest-cov>=2.0; extra == "dev"
Requires-Dist: black>=22.0; extra == "dev"
Requires-Dist: flake8>=4.0; extra == "dev"
Requires-Dist: mypy>=0.900; extra == "dev"
Requires-Dist: pre-commit>=2.15; extra == "dev"
Provides-Extra: docs
Requires-Dist: sphinx>=4.0; extra == "docs"
Requires-Dist: sphinx-rtd-theme>=1.0; extra == "docs"
Requires-Dist: myst-parser>=0.15; extra == "docs"
Provides-Extra: benchmark
Requires-Dist: memory-profiler>=0.58; extra == "benchmark"
Requires-Dist: line-profiler>=3.0; extra == "benchmark"
Requires-Dist: jupyter>=1.0; extra == "benchmark"
Requires-Dist: seaborn>=0.11; extra == "benchmark"
